README.md
setup.py
ASF/__init__.py
ASF/models.py
ASF/utils.py
ASF_IPC.egg-info/PKG-INFO
ASF_IPC.egg-info/SOURCES.txt
ASF_IPC.egg-info/dependency_links.txt
ASF_IPC.egg-info/requires.txt
ASF_IPC.egg-info/top_level.txt