Metadata-Version: 1.2
Name: ASF-IPC
Version: 2.1.0
Summary: A simple Python 3.6+ library of ArchiSteamFarm IPC API
Home-page: https://github.com/deluxghost/ASF_IPC/
Author: deluxghost
Author-email: deluxghost@gmail.com
License: GPL v3
Platform: UNKNOWN
Classifier: Development Status :: 4 - Beta
Classifier: License :: OSI Approved :: GNU General Public License v3 (GPLv3)
Classifier: Intended Audience :: Developers
Classifier: Operating System :: OS Independent
Classifier: Programming Language :: Python :: 3.6
Classifier: Topic :: Software Development :: Libraries :: Python Modules
Requires-Python: >=3.6, <4
